project/__init__.py
project/data_preprocessing/__init__.py
project/data_preprocessing/data_loader.py
project/data_preprocessing/preprocessing.py
project/models/__init__.py
project/models/model.py
prostagma/__init__.py
prostagma/performances/__init__.py
prostagma/performances/cross_validation.py
prostagma/performances/hold_out.py
prostagma/performances/performance.py
prostagma/techniques/__init__.py
prostagma/techniques/evolutionary.py
prostagma/techniques/grid_search.py
prostagma/techniques/technique.py
prostagma-0.2.dist-info/DESCRIPTION.rst
prostagma-0.2.dist-info/METADATA
prostagma-0.2.dist-info/RECORD
prostagma-0.2.dist-info/WHEEL
prostagma-0.2.dist-info/metadata.json
prostagma-0.2.dist-info/top_level.txt
